[{"title":"Musikinstrumente","items":[{"id":"bowl","name":"Klangschale"},{"id":"harp","name":"Harfe"},{"id":"bell","name":"Glöckchen"},{"id":"hang","name":"Hang"},{"id":"hang_small","name":"Kleiner Hang"}]},{"title":"Natur","items":[{"id":"fire","name":"Feuer"},{"id":"rain","name":"Regen"},{"id":"wave","name":"Wellen"},{"id":"snow_steps","name":"Schritte im Schnee"},{"id":"blizzard","name":"Schneesturm"},{"id":"rain_roof","name":"Regen auf dem Dach"},{"id":"thunderstorm","name":"Gewitter"},{"id":"stream","name":"Bach"},{"id":"waterfall","name":"Wasserfall"},{"id":"drops","name":"Tropfen"},{"id":"lava","name":"Lava"}]},{"title":"Umgebung","items":[{"id":"street","name":"Straße"},{"id":"underwater","name":"Unterwasser"},{"id":"keyboard","name":"Tastatur"},{"id":"hran","name":"Schnarchen"},{"id":"crowd","name":"Menschenmenge"}]},{"title":"Transport","items":[{"id":"train","name":"Zug"},{"id":"plane","name":"Flugzeug"},{"id":"metro","name":"U-Bahn"}]},{"title":"Haushaltsgeräte","items":[{"id":"conditioner","name":"Klimaanlage"},{"id":"fridge","name":"Kühlschrank"},{"id":"dishwasher","name":"Geschirrspüler"},{"id":"vacuum_cleaner","name":"Staubsauger"},{"id":"dryer","name":"Föhn"},{"id":"clock","name":"Uhr"}]},{"title":"Tiere","items":[{"id":"crickets","name":"Grillen"},{"id":"whales","name":"Wale"},{"id":"wolves","name":"Wölfe"},{"id":"cuckoo","name":"Kuckuck"},{"id":"horses","name":"Pferde"},{"id":"cat","name":"Katze"},{"id":"seagulls","name":"Möwen"},{"id":"frogs","name":"Frösche"},{"id":"bee","name":"Biene"},{"id":"dolphin","name":"Delfin"},{"id":"seal","name":"Seehund"}]}]